test_har/__init__.py
test_har/django_rest_har.py
test_har/requests_har.py
test_har/tests/__init__.py
test_har/tests/test_drf.py
test_har/tests/test_requests.py
test_har-0.2.dev0.dist-info/DESCRIPTION.rst
test_har-0.2.dev0.dist-info/METADATA
test_har-0.2.dev0.dist-info/RECORD
test_har-0.2.dev0.dist-info/WHEEL
test_har-0.2.dev0.dist-info/entry_points.txt
test_har-0.2.dev0.dist-info/metadata.json
test_har-0.2.dev0.dist-info/top_level.txt
test_har_drf/__init__.py
test_har_drf/serializers.py
test_har_drf/settings.py
test_har_drf/urls.py
test_har_drf/views.py
test_har_drf/wsgi.py
