Metadata-Version: 2.0
Name: test-har
Version: 0.2.dev0
Summary: Use HTTP Archive (HAR) files in Python tests
Home-page: https://github.com/rpatterson/test-har
Author: Ross Patterson
Author-email: me@rpatterson.net
License: GPL
Keywords: testing test har
Platform: UNKNOWN
Provides-Extra: tests
Requires-Dist: requests-mock; extra == 'tests'
Requires-Dist: django-setuptest; extra == 'tests'
Requires-Dist: djangorestframework; extra == 'tests'
